MANIFEST.in
README.md
requirements.txt
setup.py
flask_oslolog/__init__.py
flask_oslolog/middleware.py
flask_oslolog.egg-info/PKG-INFO
flask_oslolog.egg-info/SOURCES.txt
flask_oslolog.egg-info/dependency_links.txt
flask_oslolog.egg-info/entry_points.txt
flask_oslolog.egg-info/requires.txt
flask_oslolog.egg-info/top_level.txt