Metadata-Version: 1.1
Name: flask-oslolog
Version: 0.1
Summary: This project wraps the existing oslo.log library to providerequest logging and logger access within flask..
Home-page: https://github.com/Rackspace-DOT/flask_oslolog
Author: Rackspace Developers for Operational Tooling
Author-email: dot@rackspace.com
License: UNKNOWN
Keywords: flask,identity,auth
Platform: any
Classifier: Development Status :: 2 - Pre-Alpha
Classifier: Intended Audience :: Developers
Classifier: Topic :: Internet :: WWW/HTTP :: Dynamic Content
Classifier: Topic :: Internet :: WWW/HTTP :: WSGI :: Middleware
Classifier: Topic :: Software Development :: Libraries :: Python Modules
Classifier: Operating System :: Unix
Classifier: Operating System :: POSIX
Classifier: Programming Language :: Python :: 3.4
Classifier: Programming Language :: Python :: 3.5
